suicideproc/README.MD
suicideproc/__init__.py
suicideproc/requirements.txt
suicideproc/thirdparty.json
suicideproc-0.10.dist-info/LICENSE.rst
suicideproc-0.10.dist-info/METADATA
suicideproc-0.10.dist-info/WHEEL
suicideproc-0.10.dist-info/top_level.txt
suicideproc-0.10.dist-info/RECORD
