Metadata-Version: 2.1
Name: suicideproc
Version: 0.10
Summary: Kills the current process by using taskkill.exe
Home-page: https://github.com/hansalemaos/suicideproc
Author: Johannes Fischer
Author-email: aulasparticularesdealemaosp@gmail.com
License: MIT
Keywords: kill,processes
Classifier: Development Status :: 4 - Beta
Classifier: Programming Language :: Python :: 3 :: Only
Classifier: Programming Language :: Python :: 3.10
Classifier: Topic :: Software Development :: Libraries :: Python Modules
Classifier: Topic :: Utilities
License-File: LICENSE.rst
